ct_landscape/__init__.py
ct_landscape/_version.py
ct_landscape/ct-landscape-explorer.py
ct_landscape/ct_landscape.py
ct_landscape/readme_ct-landscape-explorer
ct_landscape/requirements.txt
ct_landscape/tools.py
ct_landscape/data/CTL_data.csv
ct_landscape/data/Fig5a.jpg
ct_landscape/data/README.md
ct_landscape/data/look_and_say.dat
ct_landscape/data/xyz/triad_0.xyz
ct_landscape/data/xyz/triad_1.xyz
ct_landscape/data/xyz/triad_10.xyz
ct_landscape/data/xyz/triad_100.xyz
ct_landscape/data/xyz/triad_101.xyz
ct_landscape/data/xyz/triad_102.xyz
ct_landscape/data/xyz/triad_103.xyz
ct_landscape/data/xyz/triad_104.xyz
ct_landscape/data/xyz/triad_105.xyz
ct_landscape/data/xyz/triad_106.xyz
ct_landscape/data/xyz/triad_107.xyz
ct_landscape/data/xyz/triad_108.xyz
ct_landscape/data/xyz/triad_109.xyz
ct_landscape/data/xyz/triad_11.xyz
ct_landscape/data/xyz/triad_110.xyz
ct_landscape/data/xyz/triad_111.xyz
ct_landscape/data/xyz/triad_112.xyz
ct_landscape/data/xyz/triad_113.xyz
ct_landscape/data/xyz/triad_114.xyz
ct_landscape/data/xyz/triad_115.xyz
ct_landscape/data/xyz/triad_116.xyz
ct_landscape/data/xyz/triad_117.xyz
ct_landscape/data/xyz/triad_118.xyz
ct_landscape/data/xyz/triad_119.xyz
ct_landscape/data/xyz/triad_12.xyz
ct_landscape/data/xyz/triad_120.xyz
ct_landscape/data/xyz/triad_121.xyz
ct_landscape/data/xyz/triad_122.xyz
ct_landscape/data/xyz/triad_123.xyz
ct_landscape/data/xyz/triad_124.xyz
ct_landscape/data/xyz/triad_125.xyz
ct_landscape/data/xyz/triad_126.xyz
ct_landscape/data/xyz/triad_127.xyz
ct_landscape/data/xyz/triad_128.xyz
ct_landscape/data/xyz/triad_129.xyz
ct_landscape/data/xyz/triad_13.xyz
ct_landscape/data/xyz/triad_130.xyz
ct_landscape/data/xyz/triad_131.xyz
ct_landscape/data/xyz/triad_132.xyz
ct_landscape/data/xyz/triad_133.xyz
ct_landscape/data/xyz/triad_134.xyz
ct_landscape/data/xyz/triad_135.xyz
ct_landscape/data/xyz/triad_136.xyz
ct_landscape/data/xyz/triad_137.xyz
ct_landscape/data/xyz/triad_138.xyz
ct_landscape/data/xyz/triad_139.xyz
ct_landscape-0.0.1.dist-info/LICENSE
ct_landscape-0.0.1.dist-info/METADATA
ct_landscape-0.0.1.dist-info/WHEEL
ct_landscape-0.0.1.dist-info/entry_points.txt
ct_landscape-0.0.1.dist-info/top_level.txt
ct_landscape-0.0.1.dist-info/RECORD
