Metadata-Version: 2.1
Name: ct-landscape
Version: 0.0.1
Summary: CT_Landscape Charge Transfer Landscape : Strategy, Methodologies, and Toolkit Development
Home-page: https://github.com/dominikusbrian/ct_landscape
Author: Dominikus Brian
Author-email: dominikusbrian@nyu.edu
License: GNU General Public License v3
Keywords: ct_landscape
Platform: UNKNOWN
Classifier: Development Status :: 2 - Pre-Alpha
Classifier: Intended Audience :: Developers
Classifier: License :: OSI Approved :: GNU General Public License v3 (GPLv3)
Classifier: Natural Language :: English
Classifier: Programming Language :: Python :: 3
Classifier: Programming Language :: Python :: 3.5
Classifier: Programming Language :: Python :: 3.6
Classifier: Programming Language :: Python :: 3.7
Classifier: Programming Language :: Python :: 3.8
Requires-Python: >=3.5
License-File: LICENSE
